Tool.py
xietestlib/__init__.py
xietestlib/xielibone.py
xietestlib-1.0.0.dist-info/License.txt
xietestlib-1.0.0.dist-info/METADATA
xietestlib-1.0.0.dist-info/WHEEL
xietestlib-1.0.0.dist-info/top_level.txt
xietestlib-1.0.0.dist-info/RECORD
