Metadata-Version: 2.1
Name: xietestlib
Version: 1.0.0
Summary: this is a test lib
Home-page: https://github.com/Miraclerice/python3Project
Author: xie
Author-email: 166@163.com
License: MIT
License-File: License.txt
